lupuxt2py/__init__.py
lupuxt2py/__main__.py
lupuxt2py/constants.py
lupuxt2py/lupusec_service.py
lupuxt2py/lupusec_types.py
lupuxt2py-0.9.0.dist-info/LICENSE.txt
lupuxt2py-0.9.0.dist-info/METADATA
lupuxt2py-0.9.0.dist-info/WHEEL
lupuxt2py-0.9.0.dist-info/top_level.txt
lupuxt2py-0.9.0.dist-info/RECORD
