Metadata-Version: 2.1
Name: lupuxt2py
Version: 0.9.0
Summary: Python project for interacting with Lupusec XT2 (Plus)
Home-page: https://github.com/ChrisKeck/lupuxt2py
Author: ChrisKeck
Author-email: keckchris@outlook.com
License: UNKNOWN
Project-URL: Bug Reports, https://github.com/chriskeck/lupuxt2py/issues
Project-URL: Funding, https://donate.pypi.org
Project-URL: Source, https://github.com/chriskeck/lupuxt2py/
Keywords: alarm,security,iot
Platform: UNKNOWN
Classifier: Development Status :: 4 - Beta
Classifier: Intended Audience :: Developers
Classifier: License :: OSI Approved :: MIT License
Classifier: Programming Language :: Python :: 3
Classifier: Programming Language :: Python :: 3.8
Classifier: Programming Language :: Python :: 3.9
Classifier: Programming Language :: Python :: 3.10
Classifier: Programming Language :: Python :: 3 :: Only
Requires-Python: >=3.8, <4
License-File: LICENSE.txt
Requires-Dist: urllib3
Requires-Dist: asyncio
Provides-Extra: dev
Requires-Dist: check-manifest ; extra == 'dev'
Provides-Extra: test
Requires-Dist: coverage ; extra == 'test'
Requires-Dist: urllib3-mock ; extra == 'test'
Requires-Dist: pytest ; extra == 'test'
Requires-Dist: requests ; extra == 'test'
Requires-Dist: six ; extra == 'test'
Requires-Dist: pytest-cov ; extra == 'test'
Requires-Dist: flake8 ; extra == 'test'
